{
  "rasa_nlu_data": {
    "common_examples": [
      {
        "text": "Hello",
        "intent": "greeting",
        "entities": []
      },
      {
        "text": "I want to know my Horoscope",
        "intent": "get_horoscope",
        "entities": []
      },
      {
        "text": "Can you please tell me my horoscope?",
        "intent": "get_horoscope",
        "entities": []
      },
      {
        "text": "Please subscribe me",
        "intent": "subscription",
        "entities": []
      },
      {
        "text": "Give me cheese pizza",
        "intent": "order_pizza",
        "entities": [
          {
            "start": 8,
            "end": 20,
            "value": "cheese pizza",
            "entity": "order_item"
          }
        ]
      }
    ],
    "regex_features": [],
    "entity_synonyms": []
  }
}